ccds/__init__.py
ccds/__main__.py
ccds/monkey_patch.py
ccds/hook_utils/__init__.py
ccds/hook_utils/configure_gh.py
ccds/hook_utils/configure_ssh.py
ccds/hook_utils/configure_vcs.py
ccds/hook_utils/cookiecutter_args.py
ccds/hook_utils/custom_config.py
ccds/hook_utils/dependencies.py
ccds/hook_utils/scaffold_cleaner.py
gatlens_opinionated_template-0.6.1.dist-info/entry_points.txt
gatlens_opinionated_template-0.6.1.dist-info/licenses/LICENSE
gatlens_opinionated_template-0.6.1.dist-info/WHEEL
gatlens_opinionated_template-0.6.1.dist-info/METADATA
gatlens_opinionated_template-0.6.1.dist-info/RECORD
