Metadata-Version: 2.4
Name: gatlens-opinionated-template
Version: 0.6.1
Summary: A modern, opinionated full-stack CookieCutter project template that prioritizes developer experience and cutting-edge tools.
Author-email: Gatlen Culp <GatlenCulp@gmail.com>, DrivenData <info@drivendata.org>
Requires-Python: >=3.10,<4
Classifier: Development Status :: 5 - Production/Stable
Classifier: Intended Audience :: Developers
Classifier: Intended Audience :: Science/Research
Classifier: License :: OSI Approved :: MIT License
Classifier: Programming Language :: Python :: 3
Classifier: Programming Language :: Python :: 3.9
Classifier: Programming Language :: Python :: 3.10
Classifier: Programming Language :: Python :: 3.11
Classifier: Programming Language :: Python :: 3.12
Classifier: Programming Language :: Python :: 3.13
Classifier: Topic :: Scientific/Engineering
Classifier: Topic :: Scientific/Engineering :: Artificial Intelligence
License-File: LICENSE
Requires-Dist: click>=8.1.0
Requires-Dist: cookiecutter>=2.6.0
Requires-Dist: loguru>=0.7.3
Requires-Dist: pydantic>=2.10.6
Requires-Dist: pymdown-extensions>=10.13
Requires-Dist: tomlkit
Project-URL: Documentation, https://gatlenculp.github.io/gatlens-opinionated-template/
Project-URL: Source Code, https://github.com/GatlenCulp/gatlens-opinionated-template
